bitunix_automated_crypto_trading/AsyncThreadRunner.py
bitunix_automated_crypto_trading/BitunixApi.py
bitunix_automated_crypto_trading/BitunixSignal.py
bitunix_automated_crypto_trading/BitunixWebSocket.py
bitunix_automated_crypto_trading/DataFrameHtmlRenderer.py
bitunix_automated_crypto_trading/NotificationManager.py
bitunix_automated_crypto_trading/SupportResistance.py
bitunix_automated_crypto_trading/TickerManager.py
bitunix_automated_crypto_trading/__init__.py
bitunix_automated_crypto_trading/bitunix.py
bitunix_automated_crypto_trading/config.py
bitunix_automated_crypto_trading/logger.py
bitunix_automated_crypto_trading/version.py
bitunix_automated_crypto_trading-3.4.0.dist-info/METADATA
bitunix_automated_crypto_trading-3.4.0.dist-info/WHEEL
bitunix_automated_crypto_trading-3.4.0.dist-info/entry_points.txt
bitunix_automated_crypto_trading-3.4.0.dist-info/top_level.txt
bitunix_automated_crypto_trading-3.4.0.dist-info/RECORD
