Metadata-Version: 2.4
Name: bitunix_automated_crypto_trading
Version: 3.4.0
Summary: Bitunix Futures Auto Trading Platform
Home-page: https://github.com/tcj2001/bitunix-automated-crypto-trading
Author: tcj2001
Author-email: thomsonmathews@hotmail.com
License: MIT
Classifier: Programming Language :: Python :: 3
Classifier: License :: OSI Approved :: MIT License
Classifier: Operating System :: OS Independent
Requires-Python: >=3.13
Requires-Dist: fastapi
Requires-Dist: uvicorn
Requires-Dist: fastapi-login
Requires-Dist: python-multipart
Requires-Dist: jinja2
Requires-Dist: python-dotenv
Requires-Dist: pydantic
Requires-Dist: pydantic-settings
Requires-Dist: websockets
Requires-Dist: requests
Requires-Dist: aiohttp
Requires-Dist: pytz
Requires-Dist: cryptography
Requires-Dist: colorama
Requires-Dist: pandas
Requires-Dist: numpy
Dynamic: author
Dynamic: author-email
Dynamic: classifier
Dynamic: home-page
Dynamic: license
Dynamic: requires-dist
Dynamic: requires-python
Dynamic: summary
